phonic/__init__.py
phonic/agents/__init__.py
phonic/agents/client.py
phonic/agents/raw_client.py
phonic/agents/requests/__init__.py
phonic/agents/requests/agents_add_custom_phone_number_response.py
phonic/agents/requests/agents_create_response.py
phonic/agents/requests/agents_delete_response.py
phonic/agents/requests/agents_get_response.py
phonic/agents/requests/agents_list_response.py
phonic/agents/requests/agents_remove_custom_phone_number_response.py
phonic/agents/requests/agents_update_response.py
phonic/agents/requests/agents_upsert_response.py
phonic/agents/requests/update_agent_request_configuration_endpoint.py
phonic/agents/requests/update_agent_request_template_variables_value.py
phonic/agents/requests/update_agent_request_tools_item.py
phonic/agents/types/__init__.py
phonic/agents/types/agents_add_custom_phone_number_response.py
phonic/agents/types/agents_create_response.py
phonic/agents/types/agents_delete_response.py
phonic/agents/types/agents_get_response.py
phonic/agents/types/agents_list_response.py
phonic/agents/types/agents_remove_custom_phone_number_response.py
phonic/agents/types/agents_update_response.py
phonic/agents/types/agents_upsert_response.py
phonic/agents/types/update_agent_request_audio_format.py
phonic/agents/types/update_agent_request_background_noise.py
phonic/agents/types/update_agent_request_configuration_endpoint.py
phonic/agents/types/update_agent_request_phone_number.py
phonic/agents/types/update_agent_request_template_variables_value.py
phonic/agents/types/update_agent_request_tools_item.py
phonic/auth/__init__.py
phonic/auth/client.py
phonic/auth/raw_client.py
phonic/auth/requests/__init__.py
phonic/auth/requests/auth_create_session_token_response.py
phonic/auth/types/__init__.py
phonic/auth/types/auth_create_session_token_response.py
phonic/client.py
phonic/conversations/__init__.py
phonic/conversations/client.py
phonic/conversations/raw_client.py
phonic/conversations/requests/__init__.py
phonic-0.30.25.dist-info/METADATA
phonic-0.30.25.dist-info/WHEEL
phonic-0.30.25.dist-info/RECORD
